ting/__init__.py
ting/cli.py
ting/context.py
ting/defaults.py
ting/exceptions.py
ting/exporter.py
ting/frkl.info
ting/ting.py
ting/ting_attributes.py
ting/ting_cast.py
ting/tings.py
ting/utils.py
ting/attributes/__init__.py
ting/attributes/rendering.py
ting/attributes/templates/.gitkeep
ting-1.0.0.dist-info/AUTHORS.rst
ting-1.0.0.dist-info/LICENSE
ting-1.0.0.dist-info/METADATA
ting-1.0.0.dist-info/WHEEL
ting-1.0.0.dist-info/top_level.txt
ting-1.0.0.dist-info/RECORD
